pyqt_single_image_graphics_view/__init__.py
pyqt_single_image_graphics_view/singleImageGraphicsView.py
pyqt_single_image_graphics_view-0.0.13.dist-info/LICENSE
pyqt_single_image_graphics_view-0.0.13.dist-info/METADATA
pyqt_single_image_graphics_view-0.0.13.dist-info/WHEEL
pyqt_single_image_graphics_view-0.0.13.dist-info/top_level.txt
pyqt_single_image_graphics_view-0.0.13.dist-info/RECORD
