Metadata-Version: 2.1
Name: pyqt-single-image-graphics-view
Version: 0.0.13
Summary: PyQt one image only QGraphicsView
Home-page: https://github.com/yjg30737/pyqt-single-image-graphics-view.git
Author: Jung Gyu Yoon
Author-email: yjg30737@gmail.com
License: MIT
Platform: UNKNOWN
License-File: LICENSE
Requires-Dist: PyQt5 (>=5.8)
